{
  "date": "2025-05-16",
  "type": "general",
  "msgs": [
    {
      "type": "string",
      "msg": "I will attend"
    },
    {
      "type": "link",
      "msg": "WebSci 2025",
      "link": "https://www.websci25.org"
    },
    {
      "type": "string",
      "msg": "at New York, NY. On May 20, I will host the tutorial"
    },
    {
      "type": "link",
      "msg": "Beyond APIs: Collecting Web Data for Research using the National Internet Observatory",
      "link": "https://national-internet-observatory.github.io/beyondapi_websci25/",
      "punctuation": "."
    },
    {
      "type": "string",
      "msg": "On May 22, I will present our paper"
    },
    {
      "type": "pub",
      "project_id": "yang2024accuracy",
      "punctuation": "."
    },
    {
      "type": "string",
      "msg": "Please come and say hi!"
    }
  ]
}